odoo/addons/web_widget_model_viewer/README.rst
odoo/addons/web_widget_model_viewer/__init__.py
odoo/addons/web_widget_model_viewer/__manifest__.py
odoo/addons/web_widget_model_viewer/example/Chair.glb
odoo/addons/web_widget_model_viewer/i18n/ca.po
odoo/addons/web_widget_model_viewer/i18n/es.po
odoo/addons/web_widget_model_viewer/i18n/pt_BR.po
odoo/addons/web_widget_model_viewer/i18n/web_widget_model_viewer.pot
odoo/addons/web_widget_model_viewer/readme/CONTRIBUTORS.rst
odoo/addons/web_widget_model_viewer/readme/CREDITS.rst
odoo/addons/web_widget_model_viewer/readme/DESCRIPTION.rst
odoo/addons/web_widget_model_viewer/readme/HISTORY.rst
odoo/addons/web_widget_model_viewer/readme/USAGE.rst
odoo/addons/web_widget_model_viewer/static/description/icon.png
odoo/addons/web_widget_model_viewer/static/description/index.html
odoo/addons/web_widget_model_viewer/static/img/Eames_Lounge_Chair.gif
odoo/addons/web_widget_model_viewer/static/img/gltfOverview.png
odoo/addons/web_widget_model_viewer/static/lib/model-viewer-legacy.js
odoo/addons/web_widget_model_viewer/static/lib/model-viewer.min.js
odoo/addons/web_widget_model_viewer/static/src/js/web_widget_model_viewer.js
odoo/addons/web_widget_model_viewer/static/src/xml/web_widget_model_viewer.xml
odoo/addons/web_widget_model_viewer/views/assets.xml
odoo12_addon_web_widget_model_viewer-12.0.2.0.0.99.dev10.dist-info/METADATA
odoo12_addon_web_widget_model_viewer-12.0.2.0.0.99.dev10.dist-info/WHEEL
odoo12_addon_web_widget_model_viewer-12.0.2.0.0.99.dev10.dist-info/top_level.txt
odoo12_addon_web_widget_model_viewer-12.0.2.0.0.99.dev10.dist-info/RECORD
