Metadata-Version: 2.1
Name: odoo12-addon-web-widget-model-viewer
Version: 12.0.2.0.0.99.dev10
Summary: Easily display interactive 3D models on the web & in AR
Home-page: https://github.com/OCA/web
Author: TAKOBI, Openindustry.it, Odoo Community Association (OCA)
Author-email: support@odoo-community.org
License: AGPL-3
Platform: UNKNOWN
Classifier: Programming Language :: Python
Classifier: Framework :: Odoo
Classifier: Framework :: Odoo :: 12.0
Classifier: License :: OSI Approved :: GNU Affero General Public License v3
Classifier: Development Status :: 4 - Beta
Requires-Python: >=3.5
Requires-Dist: odoo <12.1dev,>=12.0a
